shmm/__init__.py
shmm/functions.py
shmm/model.py
shmm-0.0.4.dist-info/METADATA
shmm-0.0.4.dist-info/WHEEL
shmm-0.0.4.dist-info/top_level.txt
shmm-0.0.4.dist-info/RECORD
